RelaxiFI/EOS_CO2.py
RelaxiFI/__init__.py
RelaxiFI/_version.py
RelaxiFI/density_depth_crustal_profiles.py
RelaxiFI/stretching_eqs.py
RelaxiFI-0.0.5.dist-info/LICENSE
RelaxiFI-0.0.5.dist-info/METADATA
RelaxiFI-0.0.5.dist-info/WHEEL
RelaxiFI-0.0.5.dist-info/top_level.txt
RelaxiFI-0.0.5.dist-info/RECORD
