Metadata-Version: 2.1
Name: RelaxiFI
Version: 0.0.5
Summary: RelaxiFI
Home-page: https://github.com/cljdevitre/RelaxiFI
Author: Charlotte Devitre
Author-email: 
License: UNKNOWN
Platform: UNKNOWN
Classifier: Programming Language :: Python :: 3
Classifier: Operating System :: OS Independent
Requires-Python: >=3.7
Requires-Dist: pandas
Requires-Dist: numpy
Requires-Dist: matplotlib
Requires-Dist: tqdm
Requires-Dist: scipy
